sidekicks/__init__.py
sidekicks/app.py
sidekicks/bridge.py
sidekicks/component.py
sidekicks/reloader.py
sidekicks/render.py
sidekicks/router.py
sidekicks/state.py
sidekicks/components/__init__.py
sidekicks/components/buttons.py
sidekicks/components/feedback.py
sidekicks/components/inputs.py
sidekicks/components/layout.py
sidekicks-0.1.0.dev0.dist-info/licenses/LICENSE
sidekicks-0.1.0.dev0.dist-info/METADATA
sidekicks-0.1.0.dev0.dist-info/WHEEL
sidekicks-0.1.0.dev0.dist-info/top_level.txt
sidekicks-0.1.0.dev0.dist-info/RECORD
